{
  "version": 2,
  "id": "template_ax3zsl",
  "name": "ファン考察ショート動画",
  "sourceUrl": "https://www.youtube.com/watch?v=6NTmwrn9k3M",
  "sourceTitle": "ワンピースの作画崩壊？ニカのせいでとんでもないことにｗｗｗ",
  "sourceChannel": "まとめブログ",
  "createdAt": "2026-04-20T10:16:48.346Z",
  "totalDuration": 59,
  "layers": [
    {
      "id": "ly_mo71iuhm_m2c31t",
      "type": "image",
      "source": "auto",
      "x": 0,
      "y": 0,
      "width": 100,
      "height": 100,
      "zIndex": 0,
      "startSec": 0,
      "endSec": 4,
      "motion": "static"
    },
    {
      "id": "ly_mo71iuhm_56x7vm",
      "type": "image",
      "source": "auto",
      "x": 0,
      "y": 0,
      "width": 100,
      "height": 100,
      "zIndex": 1,
      "startSec": 4,
      "endSec": 5,
      "motion": "static"
    },
    {
      "id": "ly_mo71iuhm_u81esv",
      "type": "image",
      "source": "auto",
      "x": 0,
      "y": 0,
      "width": 100,
      "height": 100,
      "zIndex": 2,
      "startSec": 5,
      "endSec": 10,
      "motion": "static"
    },
    {
      "id": "ly_mo71iuhm_fnumbb",
      "type": "image",
      "source": "auto",
      "x": 0,
      "y": 0,
      "width": 100,
      "height": 100,
      "zIndex": 3,
      "startSec": 10,
      "endSec": 16,
      "motion": "static"
    },
    {
      "id": "ly_mo71iuhm_8e1zme",
      "type": "image",
      "source": "auto",
      "x": 0,
      "y": 0,
      "width": 100,
      "height": 100,
      "zIndex": 4,
      "startSec": 16,
      "endSec": 23,
      "motion": "static"
    },
    {
      "id": "ly_mo71iuhm_yrqvwm",
      "type": "image",
      "source": "auto",
      "x": 0,
      "y": 0,
      "width": 100,
      "height": 100,
      "zIndex": 5,
      "startSec": 23,
      "endSec": 29,
      "motion": "static"
    },
    {
      "id": "ly_mo71iuhm_tm0e79",
      "type": "image",
      "source": "auto",
      "x": 0,
      "y": 0,
      "width": 100,
      "height": 100,
      "zIndex": 6,
      "startSec": 29,
      "endSec": 36,
      "motion": "static"
    },
    {
      "id": "ly_mo71iuhm_yvjj1h",
      "type": "image",
      "source": "auto",
      "x": 0,
      "y": 0,
      "width": 100,
      "height": 100,
      "zIndex": 7,
      "startSec": 36,
      "endSec": 42,
      "motion": "static"
    },
    {
      "id": "ly_mo71iuhm_ye6k0j",
      "type": "image",
      "source": "auto",
      "x": 0,
      "y": 0,
      "width": 100,
      "height": 100,
      "zIndex": 8,
      "startSec": 42,
      "endSec": 51,
      "motion": "static"
    },
    {
      "id": "ly_mo71iuhm_asqdn2",
      "type": "image",
      "source": "auto",
      "x": 0,
      "y": 0,
      "width": 100,
      "height": 100,
      "zIndex": 9,
      "startSec": 51,
      "endSec": 59,
      "motion": "static"
    }
  ],
  "overallPacing": "Fast-paced with quick cuts between image/manga panels and text-only screens, featuring sequentially appearing comment boxes.",
  "narrationStyle": "Fast-paced, synthetic male voice reading out text overlays.",
  "themeVibe": "Critical and humorous fan discussion"
}
